docs/__init__.py
docs/conf.py
doe2_sim_parser/__init__.py
doe2_sim_parser/__main__.py
doe2_sim_parser/_version.py
doe2_sim_parser/exceptions.py
doe2_sim_parser/parse_hourly_report.py
doe2_sim_parser/parse_report_beps.py
doe2_sim_parser/parse_report_bepu.py
doe2_sim_parser/parse_report_es_d.py
doe2_sim_parser/parse_report_ps_e.py
doe2_sim_parser/parser_report_lv_m.py
doe2_sim_parser/report.py
doe2_sim_parser/settings.py
doe2_sim_parser/sim.py
doe2_sim_parser/split_sim.py
doe2_sim_parser/update_google_spreadsheet.py
doe2_sim_parser/write_sim.py
doe2_sim_parser/utils/__init__.py
doe2_sim_parser/utils/convert_path.py
doe2_sim_parser/utils/data_types.py
DOE2_SIM_Parser-0.20.dist-info/LICENSE
DOE2_SIM_Parser-0.20.dist-info/METADATA
DOE2_SIM_Parser-0.20.dist-info/WHEEL
DOE2_SIM_Parser-0.20.dist-info/top_level.txt
DOE2_SIM_Parser-0.20.dist-info/RECORD
